gapi_helper/__init__.py
gapi_helper/common/__init__.py
gapi_helper/common/operations.py
gapi_helper/drive/README.md
gapi_helper/drive/__init__.py
gapi_helper/drive/client.py
gapi_helper/drive/file.py
gapi_helper/drive/folder.py
gapi_helper/drive/operations.py
gapi_helper/mail/README.md
gapi_helper/mail/__init__.py
gapi_helper/mail/client.py
gapi_helper/sheets/README.md
gapi_helper/sheets/__init__.py
gapi_helper/sheets/client.py
gapi_helper/sheets/operations.py
gapi_helper/sheets/range.py
gapi_helper/sheets/sheet.py
gapi_helper/sheets/spreadsheet.py
gapi_helper/tasks/README.md
gapi_helper/tasks/__init__.py
gapi_helper/tasks/cli.py
gapi_helper/tasks/dumptask.py
gapi_helper/tasks/importsheetsource.py
gapi_helper/tasks/transfertask.py
gapi_helper/tasks/types.py
gapi_helper-0.2.4.dist-info/LICENSE
gapi_helper-0.2.4.dist-info/WHEEL
gapi_helper-0.2.4.dist-info/METADATA
gapi_helper-0.2.4.dist-info/RECORD
